ctools/__init__.py
ctools/cattrs.py
ctools/colored.py
ctools/models.py
xctools-1.1.2.dist-info/LICENSE
xctools-1.1.2.dist-info/METADATA
xctools-1.1.2.dist-info/WHEEL
xctools-1.1.2.dist-info/top_level.txt
xctools-1.1.2.dist-info/RECORD
