Metadata-Version: 2.1
Name: xctools
Version: 1.1.2
Summary: output color text to terminal
Home-page: https://github.com/PengKe-x/Colored-Text
Author: PengKe
Author-email: 925330867@qq.com
Classifier: Programming Language :: Python :: 3
Classifier: License :: OSI Approved :: MIT License
Classifier: Operating System :: OS Independent
Requires-Python: >=3.6
License-File: LICENSE
